generate_languages.py
setup.py
django_modular_languages.egg-info/PKG-INFO
django_modular_languages.egg-info/SOURCES.txt
django_modular_languages.egg-info/dependency_links.txt
django_modular_languages.egg-info/top_level.txt