Metadata-Version: 1.1
Name: django-modular-languages
Version: 0.5
Summary: Simple script to manage multiple language catalogs in a django project.
Home-page: http://github.com/oscarcp/django-modular-languages
Author: Oscar Carballal Prego
Author-email: oscar.carballal@cidadania.coop
License: GPLv3
Keywords: script manage language i18n catalog django project
Platform: UNKNOWN
Classifier: Development Status :: 5 - Production/Stable
Classifier: Topic :: Software Development :: Build Tools
Classifier: License :: OSI Approved :: GNU Affero General Public License v3
Classifier: Operating System :: POSIX :: Linux
Classifier: Natural Language :: English
Classifier: Intended Audience :: Developers
